README.rst
setup.py
bin/mssql-runner
mssql_runner/__init__.py
mssql_runner/__version__.py
mssql_runner/config_wrapper.py
mssql_runner/module.py
mssql_runner.egg-info/PKG-INFO
mssql_runner.egg-info/SOURCES.txt
mssql_runner.egg-info/dependency_links.txt
mssql_runner.egg-info/requires.txt
mssql_runner.egg-info/top_level.txt