Metadata-Version: 1.1
Name: mssql-runner
Version: 0.1.6
Summary: MSSQL runner by Equinox
Home-page: UNKNOWN
Author: Equinox Fitness
Author-email: UNKNOWN
License: MIT
Platform: UNKNOWN
Classifier: Development Status :: 5 - Production/Stable
Classifier: Intended Audience :: Developers
Classifier: Natural Language :: English
Classifier: License :: OSI Approved :: MIT License
Classifier: Programming Language :: Python :: 3.6
